terradep_python/__init__.py
terradep_python/__main__.py
terradep_python/cli.py
terradep_python/core.py
terradep_python/provider-executable-template.sh.jinja2
terradep_python-0.1.1.dist-info/METADATA
terradep_python-0.1.1.dist-info/WHEEL
terradep_python-0.1.1.dist-info/entry_points.txt
terradep_python-0.1.1.dist-info/RECORD
